portela/__init__.py
portela/__main__.py
portela/daemon.py
portela/shared.py
portela-0.0.5.data/scripts/portela
portela-0.0.5.dist-info/METADATA
portela-0.0.5.dist-info/WHEEL
portela-0.0.5.dist-info/entry_points.txt
portela-0.0.5.dist-info/top_level.txt
portela-0.0.5.dist-info/zip-safe
portela-0.0.5.dist-info/RECORD
