Metadata-Version: 2.1
Name: portela
Version: 0.0.5
Summary: a simple port allocator
Home-page: https://github.com/perfecto25/portela
Author: mreider
Author-email: mike.reider@gmail.com
License: MIT
Keywords: portela port listener web server
Platform: UNKNOWN
